subnotebook/__init__.py
subnotebook/_subnotebook.py
subnotebook-0.0.1.dist-info/METADATA
subnotebook-0.0.1.dist-info/WHEEL
subnotebook-0.0.1.dist-info/licenses/LICENSE
subnotebook-0.0.1.dist-info/RECORD
