Metadata-Version: 2.4
Name: subnotebook
Version: 0.0.1
Summary: Call notebooks as functions
Project-URL: Source, https://github.com/davidbrochart/subnotebook
Project-URL: Issues, https://github.com/davidbrochart/subnotebook/issues
Author-email: David Brochart <david.brochart@gmail.com>
License: This is the MIT license: http://www.opensource.org/licenses/mit-license.php
License-File: LICENSE
Classifier: Development Status :: 4 - Beta
Classifier: Intended Audience :: Developers
Classifier: License :: OSI Approved :: MIT License
Classifier: Programming Language :: Python
Classifier: Programming Language :: Python :: 3
Classifier: Programming Language :: Python :: 3.8
Classifier: Programming Language :: Python :: 3.9
Classifier: Programming Language :: Python :: 3.10
Classifier: Programming Language :: Python :: 3.11
Classifier: Programming Language :: Python :: 3.12
Classifier: Programming Language :: Python :: 3.13
Classifier: Topic :: Database
Classifier: Typing :: Typed
Requires-Python: >=3.8
Requires-Dist: nbformat>=5
